pyax25/__init__.py
pyax25/ax25.py
pyax25-1.0.0.dist-info/LICENSE
pyax25-1.0.0.dist-info/METADATA
pyax25-1.0.0.dist-info/WHEEL
pyax25-1.0.0.dist-info/top_level.txt
pyax25-1.0.0.dist-info/RECORD
