Metadata-Version: 2.1
Name: pyax25
Version: 1.0.0
Summary: Python library to send AX25 UI packets over UDP
Home-page: https://github.com/VE3LSR/pyax25
Author: VE3LSR / VE3YCA
Author-email: projects@ve3lsr.ca
License: UNKNOWN
Platform: UNKNOWN
Classifier: Programming Language :: Python :: 3
Classifier: Operating System :: OS Independent
Requires-Dist: crcmod
Requires-Dist: bitstring
